treemun_sim/__init__.py
treemun_sim/core.py
treemun_sim/generadores.py
treemun_sim/optimization.py
treemun_sim/simulacion.py
treemun_sim/data/lookup_table.csv
treemun_sim-1.1.5.dist-info/licenses/LICENSE
treemun_sim-1.1.5.dist-info/METADATA
treemun_sim-1.1.5.dist-info/WHEEL
treemun_sim-1.1.5.dist-info/top_level.txt
treemun_sim-1.1.5.dist-info/RECORD
