Metadata-Version: 2.4
Name: treemun-sim
Version: 1.1.5
Summary: Growth, yield, and management simulator for Chilean plantation forests
Home-page: https://github.com/fulloaf/treemun
Author: Felipe Ulloa-Fierro
Author-email: felipe.ulloa@utalca.cl
Project-URL: Bug Reports, https://github.com/fulloaf/treemun/issues
Project-URL: Source, https://github.com/fulloaf/treemun
Project-URL: Documentation, https://github.com/fulloaf/treemun#readme
Keywords: plantation forest,simulation,biomass growth,management policies,optimization,forest management
Classifier: Development Status :: 4 - Beta
Classifier: Intended Audience :: Science/Research
Classifier: Topic :: Scientific/Engineering :: Information Analysis
Classifier: License :: OSI Approved :: MIT License
Classifier: Programming Language :: Python :: 3
Classifier: Programming Language :: Python :: 3.8
Classifier: Programming Language :: Python :: 3.9
Classifier: Programming Language :: Python :: 3.10
Classifier: Programming Language :: Python :: 3.11
Classifier: Programming Language :: Python :: 3.12
Requires-Python: >=3.8
License-File: LICENSE
Requires-Dist: numpy>=1.19.0
Requires-Dist: pandas>=1.2.0
Requires-Dist: pyomo>=6.0.0
Provides-Extra: dev
Requires-Dist: pytest>=6.0; extra == "dev"
Requires-Dist: pytest-cov>=2.0; extra == "dev"
Requires-Dist: black>=21.0; extra == "dev"
Requires-Dist: flake8>=3.8; extra == "dev"
Provides-Extra: solvers
Requires-Dist: pulp>=2.0; extra == "solvers"
Provides-Extra: solvers-extended
Requires-Dist: pulp>=2.0; extra == "solvers-extended"
Requires-Dist: cplex; extra == "solvers-extended"
Provides-Extra: complete
Requires-Dist: pulp>=2.0; extra == "complete"
Requires-Dist: pytest>=6.0; extra == "complete"
Requires-Dist: pytest-cov>=2.0; extra == "complete"
Requires-Dist: black>=21.0; extra == "complete"
Requires-Dist: flake8>=3.8; extra == "complete"
Dynamic: author
Dynamic: author-email
Dynamic: classifier
Dynamic: description
Dynamic: description-content-type
Dynamic: home-page
Dynamic: keywords
Dynamic: license-file
Dynamic: project-url
Dynamic: provides-extra
Dynamic: requires-dist
Dynamic: requires-python
Dynamic: summary
